tuyul_sdk/__init__.py
tuyul_sdk/_Cipher/__init__.py
tuyul_sdk/_Cipher/AES.py
tuyul_sdk/_Cipher/Password.py
tuyul_sdk/_Cipher/Salt.py
tuyul_sdk/_Connection/__init__.py
tuyul_sdk/_Connection/_async/__init__.py
tuyul_sdk/_Connection/_certificate/__init__.py
tuyul_sdk/_Connection/_certificate/cacert.pem
tuyul_sdk/_Connection/httpx.py
tuyul_sdk/_Connection/requests.py
tuyul_sdk/_Connection/utils.py
tuyul_sdk/_Database.py
tuyul_sdk/_Gmail/__init__.py
tuyul_sdk/_Gmail/Utils.py
tuyul_sdk/sql.py
tuyul_sdk/Utils/__init__.py
tuyul_sdk/Utils/_base/__init__.py
tuyul_sdk/Utils/_base/logger.py
tuyul_sdk/Utils/_base/proxy.py
tuyul_sdk/Utils/_base/Report.py
tuyul_sdk/Utils/_Color.py
tuyul_sdk/Utils/_hexbytes.py
tuyul_sdk/Utils/_input.py
tuyul_sdk/Utils/_Line.py
tuyul_sdk/Utils/_Log.py
tuyul_sdk/Utils/_Progress.py
tuyul_sdk/Utils/_Reset.py
tuyul_sdk/Utils/_UserAgent.py
tuyul_sdk-0.1.9.dist-info/WHEEL
tuyul_sdk-0.1.9.dist-info/METADATA
tuyul_sdk-0.1.9.dist-info/RECORD
